{
  "types": {
    "Address": {
      "is_main": false,
      "id": "99968fa3-b631-4854-ba67-914dd056d954",
      "functions": [
        {
          "title": "Address Text",
          "type": "Address Text",
          "where": "this Address has one Address Text",
          "role_id": "37af2869-57b3-4180-aefe-58356dda4870"
        },
        {
          "title": "all Booking",
          "type": "Booking",
          "where": "tickets for some Booking are being mailed to this Address",
          "role_id": "dee9f260-0514-429e-9751-51f398c85bc5",
          "is_list": true
        }
      ]
    },
    "Address Text": {
      "is_main": false,
      "id": "5b1cfbae-4123-475d-8e97-a38b97d1c918",
      "functions": [
        {
          "title": "Address",
          "type": "Address",
          "where": "one Address has this Address Text",
          "role_id": "67d58b7b-ea14-4dbb-87a7-223dc3f26afc"
        }
      ]
    },
    "Booking": {
      "is_main": true,
      "id": "875ac738-9759-47d7-b569-8382888ef412",
      "functions": [
        {
          "title": "involving Person",
          "type": "Person",
          "where": "this Person booked some Session for some Number of places"
        },
        {
          "title": "involving Session",
          "type": "Session",
          "where": "some Person booked this Session for some Number of places"
        },
        {
          "title": "involving Number",
          "type": "Number",
          "where": "some Person booked some Session for this Number of places"
        },
        {
          "title": "Booking Nr",
          "type": "Booking Nr",
          "where": "this Booking has one Booking Nr",
          "role_id": "fe3c5748-6ac3-43f4-839e-9621527069bc"
        },
        {
          "title": "Collection Code",
          "type": "Collection Code",
          "where": "this Booking has one Collection Code",
          "role_id": "be5aa0dc-153b-4819-b846-e6295d3ea9d5"
        },
        {
          "title": "all Allocated Seat",
          "type": "Seat",
          "where": "this Booking has some allocated-Seat",
          "role_id": "2622a39c-39b7-40e5-99d5-2df33a4e3702",
          "is_list": true
        },
        {
          "title": "Section",
          "type": "Section",
          "where": "this Booking is for seats in one Section",
          "role_id": "45c2bcde-9fc0-4f47-9817-414484119732"
        },
        {
          "title": "all Places Paid",
          "type": "Places Paid",
          "where": "some Number of places for this Booking have been paid for by some Payment Method",
          "role_id": "d1021ea0-ad87-47c4-bfa7-ed5c51ec1e9f",
          "is_list": true
        },
        {
          "title": "Address",
          "type": "Address",
          "where": "tickets for this Booking are being mailed to one Address",
          "role_id": "68a5ad4a-01f5-4abb-9302-f45048e2cbdf"
        },
        {
          "title": "tickets for Booking have been issued",
          "type": "boolean",
          "where": "tickets for this Booking have been issued",
          "role_id": "4862c8f8-6a46-4407-9c2e-0951b7504e10"
        }
      ]
    },
    "Booking Nr": {
      "is_main": false,
      "id": "740688f6-b087-4de9-babc-2ba140168bea",
      "functions": [
        {
          "title": "Booking",
          "type": "Booking",
          "where": "one Booking has this Booking Nr",
          "role_id": "6d079d4d-9a0d-4421-81ec-8ad1e2ef156f"
        }
      ]
    },
    "Cinema": {
      "is_main": true,
      "id": "3b6a538e-7000-47d2-8395-52be0bf1a627",
      "functions": [
        {
          "title": "Cinema ID",
          "type": "Cinema ID",
          "where": "this Cinema has one Cinema ID",
          "role_id": "75809bf0-6a2d-4cd3-9942-e469293654e0"
        },
        {
          "title": "Name",
          "type": "Name",
          "where": "this Cinema has one Name",
          "role_id": "84389bc3-c764-4dd1-ba6b-862dea4575e9"
        },
        {
          "title": "all Section",
          "type": "Section",
          "where": "this Cinema provides allocated seating in some Section",
          "role_id": "f4f43577-49cc-422a-b228-5f58f7beb953",
          "is_list": true
        },
        {
          "title": "all Session",
          "type": "Session",
          "where": "this Cinema shows some Film on some Session Time",
          "role_id": "739e7f60-842b-4aa4-92d0-6b52c1f9fe83",
          "is_list": true
        },
        {
          "title": "all Row",
          "type": "Row",
          "where": "some Row is in this Cinema",
          "role_id": "a1774517-b8db-47be-bc9c-20987e842c07",
          "is_list": true
        },
        {
          "title": "all Ticket Pricing",
          "type": "Ticket Pricing",
          "where": "tickets on some Session Time at this Cinema in some Section for some High Demand have some Price",
          "role_id": "3f3e1764-1d05-4ff1-8fdd-9fe68ed89985",
          "is_list": true
        }
      ]
    },
    "Cinema ID": {
      "is_main": false,
      "id": "ca445dbc-17a9-43a9-a8e6-a763e3914cda",
      "functions": [
        {
          "title": "Cinema",
          "type": "Cinema",
          "where": "one Cinema has this Cinema ID",
          "role_id": "952b9e23-cfd3-4c3f-bd6c-6ee7c3a14f8d"
        }
      ]
    },
    "Collection Code": {
      "is_main": false,
      "id": "9fec2dc5-bf9d-4f88-95fe-1f9f33369194",
      "functions": [
        {
          "title": "all Booking",
          "type": "Booking",
          "where": "some Booking has this Collection Code",
          "role_id": "32e97311-47a7-40d3-a429-8ea4757a4592",
          "is_list": true
        }
      ]
    },
    "Day": {
      "is_main": false,
      "id": "2602d101-087a-4cb9-8331-4dc108deb811",
      "functions": [
        {
          "title": "all Session Time",
          "type": "Session Time",
          "where": "some Session Time is on this Day",
          "role_id": "fdf7752e-e6de-4f27-a6ab-ab1e081e752c",
          "is_list": true
        }
      ]
    },
    "Encrypted Password": {
      "is_main": false,
      "id": "f513435b-dd0a-4a85-b7ff-f4597377b5ab",
      "functions": [
        {
          "title": "all Person",
          "type": "Person",
          "where": "some Person has this Encrypted Password",
          "role_id": "a1435c7e-e88e-432f-9167-c0d5bb275f91",
          "is_list": true
        }
      ]
    },
    "Film": {
      "is_main": true,
      "id": "0390ccf0-bc21-4dc9-a067-b5e944264221",
      "functions": [
        {
          "title": "all Session",
          "type": "Session",
          "where": "some Cinema shows this Film on some Session Time",
          "role_id": "9eb5eab4-1c48-4193-a0b0-0091351ecd7c",
          "is_list": true
        },
        {
          "title": "Film ID",
          "type": "Film ID",
          "where": "this Film has one Film ID",
          "role_id": "70e5bb5b-c554-4cd9-97cd-ed2695446971"
        },
        {
          "title": "Name",
          "type": "Name",
          "where": "this Film has one Name",
          "role_id": "bfbbfd13-5c6d-4ad9-af77-6fd8ac141562"
        },
        {
          "title": "Year",
          "type": "Year",
          "where": "this Film was made in one Year",
          "role_id": "b3fa0470-697f-4b0e-b5be-13ff6b336555"
        }
      ]
    },
    "Film ID": {
      "is_main": false,
      "id": "d6358108-e0e4-41ad-b922-f286fa035311",
      "functions": [
        {
          "title": "Film",
          "type": "Film",
          "where": "one Film has this Film ID",
          "role_id": "e4744c84-c3ab-46ab-9063-25fbfb90869f"
        }
      ]
    },
    "High Demand": {
      "is_main": false,
      "id": "0b5ffbaa-b86a-45cb-b836-966d6cb5e8da",
      "functions": [
        {
          "title": "all Ticket Pricing",
          "type": "Ticket Pricing",
          "where": "tickets on some Session Time at some Cinema in some Section for this High Demand have some Price",
          "role_id": "7c7678a3-5ae7-4d4e-9627-7506634b6b27",
          "is_list": true
        }
      ]
    },
    "Hour": {
      "is_main": false,
      "id": "ca3f07d2-accd-434a-b524-6bf3301f48e8",
      "functions": [
        {
          "title": "all Session Time",
          "type": "Session Time",
          "where": "some Session Time is at this Hour",
          "role_id": "0c60ad63-9abf-4148-8c0e-22be5cce5514",
          "is_list": true
        }
      ]
    },
    "Minute": {
      "is_main": false,
      "id": "5bed06bf-09ca-4fbc-90fd-8b1d7a7b9bac",
      "functions": [
        {
          "title": "all Session Time",
          "type": "Session Time",
          "where": "some Session Time is at this Minute",
          "role_id": "3567648d-2aa4-4de5-ab11-fe332b4c7808",
          "is_list": true
        }
      ]
    },
    "Month": {
      "is_main": false,
      "id": "6d5362b3-11c4-4fc2-afe4-798698767a40",
      "functions": [
        {
          "title": "Month Nr",
          "type": "Month Nr",
          "where": "this Month has one Month Nr",
          "role_id": "45782800-9421-4bae-93da-010f4077b740"
        },
        {
          "title": "all Session Time",
          "type": "Session Time",
          "where": "some Session Time is in this Month",
          "role_id": "f1c8123d-0a50-4408-a06a-ac0927bea753",
          "is_list": true
        }
      ]
    },
    "Month Nr": {
      "is_main": false,
      "id": "a172f48f-8e8f-42c2-af99-5842f0b04cda",
      "functions": [
        {
          "title": "Month",
          "type": "Month",
          "where": "one Month has this Month Nr",
          "role_id": "16921b88-ee62-4fb5-a4fc-0dab2eabd98c"
        }
      ]
    },
    "Name": {
      "is_main": false,
      "id": "ff186cf6-6b7e-4f8c-80dd-53d798d4551e",
      "functions": [
        {
          "title": "Cinema",
          "type": "Cinema",
          "where": "one Cinema has this Name",
          "role_id": "318cf461-bbf1-4046-9f8c-4b3c51efaebf"
        },
        {
          "title": "all Film",
          "type": "Film",
          "where": "some Film has this Name",
          "role_id": "7d281ac8-1145-42b1-9720-08b4b440fb07",
          "is_list": true
        },
        {
          "title": "Person",
          "type": "Person",
          "where": "one Person has this login-Name",
          "role_id": "e7d5f8b4-d51d-4e19-9e54-f385fc51b59d"
        }
      ]
    },
    "Number": {
      "is_main": false,
      "id": "93dfa398-f029-4c3b-8903-70d1ca6d38e9",
      "functions": [
        {
          "title": "all Places Paid",
          "type": "Places Paid",
          "where": "this Number of places for some Booking have been paid for by some Payment Method",
          "role_id": "1636a101-7aff-47b6-82b1-b521718f5963",
          "is_list": true
        },
        {
          "title": "all Booking",
          "type": "Booking",
          "where": "some Person booked some Session for this Number of places",
          "role_id": "dda7354c-444c-4d3b-9115-0e516a6ae2d2",
          "is_list": true
        }
      ]
    },
    "Payment Method": {
      "is_main": false,
      "id": "63f1429e-b7c2-4ba2-bbfd-52db5b3ac1b9",
      "functions": [
        {
          "title": "all Places Paid",
          "type": "Places Paid",
          "where": "some Number of places for some Booking have been paid for by this Payment Method",
          "role_id": "357849ad-175b-4f60-9683-78e4e88b60a4",
          "is_list": true
        },
        {
          "title": "Payment Method Code",
          "type": "Payment Method Code",
          "where": "this Payment Method has one Payment Method Code",
          "role_id": "5b8a5ff5-470f-4732-9b7c-a52fa305dc66"
        }
      ]
    },
    "Payment Method Code": {
      "is_main": false,
      "id": "41e7699b-dee9-4f40-b798-f5f008b7ce3c",
      "functions": [
        {
          "title": "Payment Method",
          "type": "Payment Method",
          "where": "one Payment Method has this Payment Method Code",
          "role_id": "019447ec-f816-470b-9487-196a6d904aa6"
        }
      ]
    },
    "Person": {
      "is_main": true,
      "id": "c22d1f24-2b51-4981-9952-f2e12e53a7ee",
      "functions": [
        {
          "title": "all Booking",
          "type": "Booking",
          "where": "this Person booked some Session for some Number of places",
          "role_id": "cbe439fd-4982-471a-b4f9-7a2371b78852",
          "is_list": true
        },
        {
          "title": "Encrypted Password",
          "type": "Encrypted Password",
          "where": "this Person has one Encrypted Password",
          "role_id": "99434142-7014-49b5-ae78-e4d0c7c87fe0"
        },
        {
          "title": "Person ID",
          "type": "Person ID",
          "where": "this Person has one Person ID",
          "role_id": "b061d7a0-f684-46d1-8e10-1a3922756c0c"
        },
        {
          "title": "Login Name",
          "type": "Name",
          "where": "this Person has one login-Name",
          "role_id": "2f9dd9a0-6b3f-419e-a27d-9e0332aeff6a"
        }
      ]
    },
    "Person ID": {
      "is_main": false,
      "id": "dedfbdff-923f-4f98-8d14-c6a2ab4635f0",
      "functions": [
        {
          "title": "Person",
          "type": "Person",
          "where": "one Person has this Person ID",
          "role_id": "55f424e9-28df-46ab-a025-0e27e8465035"
        }
      ]
    },
    "Places Paid": {
      "is_main": true,
      "id": "7c4307c0-d0f8-48d5-8459-bc5d603f50a4",
      "functions": [
        {
          "title": "involving Number",
          "type": "Number",
          "where": "this Number of places for some Booking have been paid for by some Payment Method"
        },
        {
          "title": "involving Booking",
          "type": "Booking",
          "where": "some Number of places for this Booking have been paid for by some Payment Method"
        },
        {
          "title": "involving Payment Method",
          "type": "Payment Method",
          "where": "some Number of places for some Booking have been paid for by this Payment Method"
        }
      ]
    },
    "Price": {
      "is_main": false,
      "id": "0e5544ea-6561-4bde-983c-46b9e13faa32",
      "functions": [
        {
          "title": "all Ticket Pricing",
          "type": "Ticket Pricing",
          "where": "tickets on some Session Time at some Cinema in some Section for some High Demand have this Price",
          "role_id": "4b22ca03-83d8-4dd6-9f72-b22052088f8c",
          "is_list": true
        }
      ]
    },
    "Row": {
      "is_main": false,
      "id": "7a9c1ff8-57d2-4dad-9fa8-067ace2030cf",
      "functions": [
        {
          "title": "Row Nr",
          "type": "Row Nr",
          "where": "this Row has one Row Nr",
          "role_id": "d3da7e87-71af-4a62-8861-1d576b68a431"
        },
        {
          "title": "Cinema",
          "type": "Cinema",
          "where": "this Row is in one Cinema",
          "role_id": "ae9b1d52-d019-428d-a57e-e2753af49525"
        },
        {
          "title": "all Seat",
          "type": "Seat",
          "where": "some Seat is in this Row",
          "role_id": "ade8d16d-4fbb-4d84-838c-75cdb31031f9",
          "is_list": true
        }
      ]
    },
    "Row Nr": {
      "is_main": false,
      "id": "03db4cba-dbc0-4091-ae8c-b0e50752edd9",
      "functions": [
        {
          "title": "all Row",
          "type": "Row",
          "where": "some Row has this Row Nr",
          "role_id": "e9ba6bed-ce81-461e-9e3c-b102166f0c2b",
          "is_list": true
        }
      ]
    },
    "Seat": {
      "is_main": true,
      "id": "3c93241b-6fe9-465b-9f66-2a63d662cab5",
      "functions": [
        {
          "title": "all Booking",
          "type": "Booking",
          "where": "some Booking has this allocated-Seat",
          "role_id": "0749de1a-f590-45ee-97f9-b3a610f87efe",
          "is_list": true
        },
        {
          "title": "Seat Number",
          "type": "Seat Number",
          "where": "this Seat has one Seat Number",
          "role_id": "7ca9865b-8c67-44f3-b45c-191d20932cd5"
        },
        {
          "title": "Row",
          "type": "Row",
          "where": "this Seat is in one Row",
          "role_id": "8bbcc64d-59fd-46a3-adf9-602167f26a83"
        },
        {
          "title": "Section",
          "type": "Section",
          "where": "this Seat is in one Section",
          "role_id": "7c58d46f-12ab-47e7-b294-eeeed8be0400"
        }
      ]
    },
    "Seat Number": {
      "is_main": false,
      "id": "276c6e17-3958-45d7-88c1-27f7cff12ada",
      "functions": [
        {
          "title": "all Seat",
          "type": "Seat",
          "where": "some Seat has this Seat Number",
          "role_id": "dcbbafde-2fd2-4848-a1d6-b505460a2ef4",
          "is_list": true
        }
      ]
    },
    "Section": {
      "is_main": false,
      "id": "0b6da0d1-bf92-4699-bf76-a6aa53457e8a",
      "functions": [
        {
          "title": "all Booking",
          "type": "Booking",
          "where": "some Booking is for seats in this Section",
          "role_id": "57f4a55e-c7b8-42c2-af58-1b94cbae1ee6",
          "is_list": true
        },
        {
          "title": "all Cinema",
          "type": "Cinema",
          "where": "some Cinema provides allocated seating in this Section",
          "role_id": "4eab91de-d8bd-4f75-82cb-ac928bdd3dd2",
          "is_list": true
        },
        {
          "title": "all Seat",
          "type": "Seat",
          "where": "some Seat is in this Section",
          "role_id": "7d408400-fcd5-49cb-9c6c-81d9f5559f19",
          "is_list": true
        },
        {
          "title": "Section Name",
          "type": "Section Name",
          "where": "this Section has one Section Name",
          "role_id": "62e57afd-ab9e-4c9e-9dd4-19c1d422b703"
        },
        {
          "title": "all Ticket Pricing",
          "type": "Ticket Pricing",
          "where": "tickets on some Session Time at some Cinema in this Section for some High Demand have some Price",
          "role_id": "c7a7eddb-e0b7-43ba-b705-607197632f82",
          "is_list": true
        }
      ]
    },
    "Section Name": {
      "is_main": false,
      "id": "a9187f5d-5898-44c2-8bed-01ddb9ffd8ce",
      "functions": [
        {
          "title": "Section",
          "type": "Section",
          "where": "one Section has this Section Name",
          "role_id": "a1a872fb-d0cd-4a86-8cf7-1c131c5a7a7b"
        }
      ]
    },
    "Session": {
      "is_main": true,
      "id": "23b044e3-1441-46cf-a09a-ca5f1d6b1ca9",
      "functions": [
        {
          "title": "involving Cinema",
          "type": "Cinema",
          "where": "this Cinema shows some Film on some Session Time"
        },
        {
          "title": "involving Film",
          "type": "Film",
          "where": "some Cinema shows this Film on some Session Time"
        },
        {
          "title": "involving Session Time",
          "type": "Session Time",
          "where": "some Cinema shows some Film on this Session Time"
        },
        {
          "title": "all Booking",
          "type": "Booking",
          "where": "some Person booked this Session for some Number of places",
          "role_id": "84d507c0-d7d3-413b-90b8-39f5ed544340",
          "is_list": true
        },
        {
          "title": "Session is high-demand",
          "type": "boolean",
          "where": "this Session is high-demand",
          "role_id": "ccb67720-be1a-467b-9371-734c2c314d85"
        },
        {
          "title": "Session uses allocated seating",
          "type": "boolean",
          "where": "this Session uses allocated seating",
          "role_id": "45e9e355-d859-4926-a240-19e228ab19c4"
        }
      ]
    },
    "Session Time": {
      "is_main": false,
      "id": "78a946fe-5783-41cf-8248-27de9fc06dc1",
      "functions": [
        {
          "title": "all Session",
          "type": "Session",
          "where": "some Cinema shows some Film on this Session Time",
          "role_id": "01365923-dd9e-43f0-93d9-030c992c3992",
          "is_list": true
        },
        {
          "title": "Hour",
          "type": "Hour",
          "where": "this Session Time is at one Hour",
          "role_id": "78062556-585c-4bd4-8823-e6f77ac76e00"
        },
        {
          "title": "Minute",
          "type": "Minute",
          "where": "this Session Time is at one Minute",
          "role_id": "b707bf97-1298-4e7e-ab07-458f1f65ddcc"
        },
        {
          "title": "Month",
          "type": "Month",
          "where": "this Session Time is in one Month",
          "role_id": "e3144f90-04b1-433e-9fc8-664ff411c04f"
        },
        {
          "title": "Year",
          "type": "Year",
          "where": "this Session Time is in one Year",
          "role_id": "38665b56-a69b-4dfb-9196-23012e3438d4"
        },
        {
          "title": "Day",
          "type": "Day",
          "where": "this Session Time is on one Day",
          "role_id": "2e20b47d-ac3e-44f9-82dd-90ed040ac722"
        },
        {
          "title": "all Ticket Pricing",
          "type": "Ticket Pricing",
          "where": "tickets on this Session Time at some Cinema in some Section for some High Demand have some Price",
          "role_id": "8967f471-d229-43de-8ef8-034ffc750755",
          "is_list": true
        }
      ]
    },
    "Ticket Pricing": {
      "is_main": true,
      "id": "1e261591-50a6-4df6-adf1-c55c19e93e6a",
      "functions": [
        {
          "title": "involving Session Time",
          "type": "Session Time",
          "where": "tickets on this Session Time at some Cinema in some Section for some High Demand have some Price"
        },
        {
          "title": "involving Cinema",
          "type": "Cinema",
          "where": "tickets on some Session Time at this Cinema in some Section for some High Demand have some Price"
        },
        {
          "title": "involving Section",
          "type": "Section",
          "where": "tickets on some Session Time at some Cinema in this Section for some High Demand have some Price"
        },
        {
          "title": "involving High Demand",
          "type": "High Demand",
          "where": "tickets on some Session Time at some Cinema in some Section for this High Demand have some Price"
        },
        {
          "title": "involving Price",
          "type": "Price",
          "where": "tickets on some Session Time at some Cinema in some Section for some High Demand have this Price"
        }
      ]
    },
    "Year": {
      "is_main": false,
      "id": "405165a7-2aab-4fe6-9909-8292ff45f309",
      "functions": [
        {
          "title": "all Film",
          "type": "Film",
          "where": "some Film was made in this Year",
          "role_id": "76835670-4e74-47b5-8b9c-3e0edfc035c1",
          "is_list": true
        },
        {
          "title": "all Session Time",
          "type": "Session Time",
          "where": "some Session Time is in this Year",
          "role_id": "e6bcd943-cc8d-4f1b-9706-c7a1f48518c7",
          "is_list": true
        },
        {
          "title": "Year Nr",
          "type": "Year Nr",
          "where": "this Year has one Year Nr",
          "role_id": "fef670f7-e944-457d-813a-6f18a2af6da7"
        }
      ]
    },
    "Year Nr": {
      "is_main": false,
      "id": "df1a3846-0fb4-4a93-8804-980cef9f7a69",
      "functions": [
        {
          "title": "Year",
          "type": "Year",
          "where": "one Year has this Year Nr",
          "role_id": "e2d151ab-2e01-46d5-9703-8ee8d9851069"
        }
      ]
    }
  }
}
